pypluto/Pluto.py
pypluto/__init__.py
pypluto_christ-0.2.0.dist-info/LICENSE
pypluto_christ-0.2.0.dist-info/METADATA
pypluto_christ-0.2.0.dist-info/WHEEL
pypluto_christ-0.2.0.dist-info/top_level.txt
pypluto_christ-0.2.0.dist-info/RECORD
