Metadata-Version: 2.1
Name: pypluto-christ
Version: 0.2.0
Summary: A library for controlling Pluto drones for the Christ University projects
Home-page: https://github.com/Drone-Club-ChristUniversity/plutoControlUpdated.git
Author: Shrey Jain
Author-email: shrey.jain@mca.christuniversity.in
Classifier: Programming Language :: Python :: 3
Classifier: License :: OSI Approved :: MIT License
Classifier: Operating System :: OS Independent
License-File: LICENSE
